syspector/__init__.py
syspector/api.py
syspector/cli.py
syspector/core.py
syspector/plugins.py
syspector/utils.py
syspector-0.1.0.dist-info/licenses/LICENSE
syspector-0.1.0.dist-info/METADATA
syspector-0.1.0.dist-info/WHEEL
syspector-0.1.0.dist-info/top_level.txt
syspector-0.1.0.dist-info/RECORD
